{
    "items": [
        {
            "id": 1,
            "name": "範例商品",
            "category": "飲料",
            "quantity": 100,
            "unit": "瓶",
            "cost_price": 50,
            "selling_price": 80,
            "min_stock": 20,
            "supplier": "範例供應商",
            "last_restock": "2024-01-01",
            "created_at": "2024-01-01",
            "updated_at": "2024-01-01"
        }
    ],
    "categories": [
        "飲料",
        "食品",
        "日用品"
    ],
    "suppliers": [
        {
            "id": 1,
            "name": "範例供應商",
            "contact": "0912345678",
            "email": "supplier@example.com",
            "address": "台北市信義區",
            "created_at": "2024-01-01"
        }
    ],
    "settings": {
        "low_stock_alert": true,
        "alert_threshold": 20,
        "auto_restock": false,
        "restock_threshold": 30
    }
} 